template_from_equation/__init__.py
template_from_equation/template_from_equation.py
template_from_equation-0.1.2.dist-info/LICENSE
template_from_equation-0.1.2.dist-info/METADATA
template_from_equation-0.1.2.dist-info/WHEEL
template_from_equation-0.1.2.dist-info/top_level.txt
template_from_equation-0.1.2.dist-info/RECORD
