Metadata-Version: 2.1
Name: template-from-equation
Version: 0.1.2
Summary: Create template from equation
Home-page: https://github.com/doubleBite/Template-from-Equation
Author: Shih-hong Tsai
Author-email: doublebite@iis.sinica.edu.tw
License: MIT
Platform: UNKNOWN
Classifier: Programming Language :: Python :: 3
Classifier: Operating System :: OS Independent
